huaweicloudsdkobs/__init__.py
huaweicloudsdkobs/v1/__init__.py
huaweicloudsdkobs/v1/obs_async_client.py
huaweicloudsdkobs/v1/obs_client.py
huaweicloudsdkobs/v1/obs_credentials.py
huaweicloudsdkobs/v1/obs_signer.py
huaweicloudsdkobs/v1/model/__init__.py
huaweicloudsdkobs/v1/model/access_control_list.py
huaweicloudsdkobs/v1/model/bucket.py
huaweicloudsdkobs/v1/model/buckets.py
huaweicloudsdkobs/v1/model/common_prefixes.py
huaweicloudsdkobs/v1/model/contents.py
huaweicloudsdkobs/v1/model/copy_object_request.py
huaweicloudsdkobs/v1/model/copy_object_response.py
huaweicloudsdkobs/v1/model/create_bucket_request.py
huaweicloudsdkobs/v1/model/create_bucket_request_body.py
huaweicloudsdkobs/v1/model/create_bucket_response.py
huaweicloudsdkobs/v1/model/delete_bucket_customdomain_request.py
huaweicloudsdkobs/v1/model/delete_bucket_customdomain_response.py
huaweicloudsdkobs/v1/model/delete_bucket_request.py
huaweicloudsdkobs/v1/model/delete_bucket_response.py
huaweicloudsdkobs/v1/model/delete_object.py
huaweicloudsdkobs/v1/model/delete_object_request.py
huaweicloudsdkobs/v1/model/delete_object_response.py
huaweicloudsdkobs/v1/model/delete_objects_request.py
huaweicloudsdkobs/v1/model/delete_objects_request_body.py
huaweicloudsdkobs/v1/model/delete_objects_response.py
huaweicloudsdkobs/v1/model/delete_result_deleted.py
huaweicloudsdkobs/v1/model/delete_result_error.py
huaweicloudsdkobs/v1/model/domains.py
huaweicloudsdkobs/v1/model/filter_object.py
huaweicloudsdkobs/v1/model/filter_rule.py
huaweicloudsdkobs/v1/model/function_stage_configuration.py
huaweicloudsdkobs/v1/model/get_bucket_acl_request.py
huaweicloudsdkobs/v1/model/get_bucket_acl_response.py
huaweicloudsdkobs/v1/model/get_bucket_customdomain_request.py
huaweicloudsdkobs/v1/model/get_bucket_customdomain_response.py
huaweicloudsdkobs/v1/model/get_bucket_metadata_request.py
huaweicloudsdkobs/v1/model/get_bucket_metadata_response.py
huaweicloudsdkobs/v1/model/get_bucket_notification_request.py
huaweicloudsdkobs-3.1.184.dist-info/METADATA
huaweicloudsdkobs-3.1.184.dist-info/WHEEL
huaweicloudsdkobs-3.1.184.dist-info/licenses/LICENSE
huaweicloudsdkobs-3.1.184.dist-info/RECORD
